Workbook
Name Aporte: Planilha1!$D$15
Name patrimonio: Planilha1!$D$18
Name qtd_anos: Planilha1!$D$16
Name Rendimento_carteira: Planilha1!$D$10
Name salario: Planilha1!$D$9
Name sugest_invest: Planilha1!$D$11
Name Taxa_mensal: Planilha1!$D$17

Sheet Planilha1
A1: INVESTIMENTOS EM FUNDOS IMOBILIÁRIOS
B7: CONFIGURAÇÕES
B9: Salário | D9: 2000
B10: Rendimento Carteira | D10: 0.009
B11: Sugestão de Investimento (30%) | D11: =D9*30% -> 600
B13: INVESTIMENTO MENSAL
B15: Quanto investir por mês? | D15: 200
B16: Por quantos anos? | D16: 5
B17: Taxa de Rendimento mensal? | D17: 0.01079
B18: Patrimônio acumulado? | D18: =FV(Taxa_mensal,qtd_anos*12,Aporte*-1) -> 16755.383
B19: Dividendos mensais | D19: =patrimonio*Rendimento_carteira -> 150.79845
B21: CENÁRIOS | D21: Dividendo
A22: 2 | B22: Quanto em 2 Anos? | C22: =FV($D$17,A$22*12,$D$15*-1) -> 5445.5255 | D22: =C22*Rendimento_carteira -> 49.009729
A23: 5 | B23: Quanto em 5 Anos? | C23: =FV($D$17,A$23*12,$D$15*-1) -> 16755.383 | D23: =C23*Rendimento_carteira -> 150.79845
A24: 10 | B24: Quanto em 10 Anos? | C24: =FV($D$17,A$24*12,$D$15*-1) -> 48656.843 | D24: =C24*Rendimento_carteira -> 437.91158
A25: 20 | B25: Quanto em 20 Anos? | C25: =FV($D$17,A$25*12,$D$15*-1) -> 225039.68 | D25: =C25*Rendimento_carteira -> 2025.3571
A26: 30 | B26: Quanto em 30 Anos? | C26: =FV($D$17,A$26*12,$D$15*-1) -> 864433.93 | D26: =C26*Rendimento_carteira -> 7779.9054
B28: PERFIL | C28: Conservador
B29: VALOR A SER INVESTIDO POR MÊS | C29: =Aporte -> 200
B31: TIPO DE FII | C31: Percentual Sugerido | D31: Valores
B32: Papel | C32: =VLOOKUP($C$28&"-"&B32,Planilha2!$A1:$D20,4,FALSE) -> 0.3 | D32: =C32*$C$29 -> 60
B33: Tijolo | C33: =VLOOKUP($C$28&"-"&B33,Planilha2!$A2:$D21,4,FALSE) -> 0.5 | D33: =C33*$C$29 -> 100
B34: Híbridos | C34: =VLOOKUP($C$28&"-"&B34,Planilha2!$A3:$D22,4,FALSE) -> 0.1 | D34: =C34*$C$29 -> 20
B35: FOFs | C35: =VLOOKUP($C$28&"-"&B35,Planilha2!$A4:$D23,4,FALSE) -> 0.1 | D35: =C35*$C$29 -> 20
B36: Desenvolvimento | C36: =VLOOKUP($C$28&"-"&B36,Planilha2!$A5:$D24,4,FALSE) -> 0 | D36: =C36*$C$29 -> 0
B37: Hotelarias | C37: =VLOOKUP($C$28&"-"&B37,Planilha2!$A6:$D25,4,FALSE) -> 0 | D37: =C37*$C$29 -> 0
D38: =SUM(D32:D37) -> 200

Sheet Planilha2
A2: CHAVE | B2: PERFIL | C2: TIPO DE FII | D2: %
A3: =B3&"-"&C3 -> Conservador-Papel | B3: Conservador | C3: Papel | D3: 0.3
A4: =B4&"-"&C4 -> Conservador-Tijolo | B4: Conservador | C4: Tijolo | D4: 0.5
A5: =B5&"-"&C5 -> Conservador-Híbridos | B5: Conservador | C5: Híbridos | D5: 0.1
A6: =B6&"-"&C6 -> Conservador-FOFs | B6: Conservador | C6: FOFs | D6: 0.1
A7: =B7&"-"&C7 -> Conservador-Desenvolvimento | B7: Conservador | C7: Desenvolvimento | D7: 0
A8: =B8&"-"&C8 -> Conservador-Hotelarias | B8: Conservador | C8: Hotelarias | D8: 0
A9: =B9&"-"&C9 -> Moderado-Papel | B9: Moderado | C9: Papel | D9: 0.32
A10: =B10&"-"&C10 -> Moderado-Tijolo | B10: Moderado | C10: Tijolo | D10: 0.35
A11: =B11&"-"&C11 -> Moderado-Híbridos | B11: Moderado | C11: Híbridos | D11: 0.08
A12: =B12&"-"&C12 -> Moderado-FOFs | B12: Moderado | C12: FOFs | D12: 0.05
A13: =B13&"-"&C13 -> Moderado-Desenvolvimento | B13: Moderado | C13: Desenvolvimento | D13: 0.1
A14: =B14&"-"&C14 -> Moderado-Hotelarias | B14: Moderado | C14: Hotelarias | D14: 0.1
... A20: =B20&"-"&C20 -> Agressivo-Hotelarias | B20: Agressivo | C20: Hotelarias | D20: 0.1
